deepsea/__init__.py
deepsea/data.py
deepsea/evaluate.py
deepsea/evaluate_test_set_segmentation.py
deepsea/evaluate_test_set_tracking.py
deepsea/loss.py
deepsea/measure_MOTA.py
deepsea/model.py
deepsea/segmentation_transforms.py
deepsea/test_single_image_segmentation.py
deepsea/test_single_set_tracking.py
deepsea/tracker_transforms.py
deepsea/train_segmentation.py
deepsea/train_tracker.py
deepsea/utils.py
deepsea/trained_models/__init__.py
deepsea/trained_models/segmentation.pth
deepsea/trained_models/tracker.pth
deepsea-0.0.3.dist-info/METADATA
deepsea-0.0.3.dist-info/WHEEL
deepsea-0.0.3.dist-info/licenses/LICENSE
deepsea-0.0.3.dist-info/RECORD
