Metadata-Version: 2.1
Name: deepsea
Version: 0.0.3
Summary: deepsea is a package to segment and track single cells over the time-lapse phase contrast microscopy image sequences
Project-URL: Homepage, https://github.com/abzargar/DeepSea
Project-URL: Bug Tracker, https://github.com/abzargar/DeepSea/issues
Author-email: Abolfazl Zargari <abzargar@ucsc.edu>
License-File: LICENSE
Requires-Python: >=3.8
